applyai_vision/APIClass.py
applyai_vision/__init__.py
applyai_vision/applyai_logfiles.py
applyai_vision/config.py
applyai_vision/job.py
applyai_vision/logfiles.py
applyai_vision/memStore.py
applyai_vision/plugin.py
applyai_vision/server.py
applyai_vision/stats.py
applyai_vision/tools.py
applyai_vision-0.6.dist-info/LICENSE
applyai_vision-0.6.dist-info/METADATA
applyai_vision-0.6.dist-info/WHEEL
applyai_vision-0.6.dist-info/top_level.txt
applyai_vision-0.6.dist-info/RECORD
