Metadata-Version: 2.1
Name: applyai-vision
Version: 0.6
Summary: A small example package
Home-page: https://github.com/pypa/sampleproject
Author: LukasGardner
Author-email: lukas.gardner@gardner-ag.com
License: UNKNOWN
Platform: UNKNOWN
Classifier: Programming Language :: Python :: 3
Classifier: License :: OSI Approved :: MIT License
Classifier: Operating System :: OS Independent
Requires-Python: >=3.6
Requires-Dist: cherrypy
Requires-Dist: datetime
Requires-Dist: regex
Requires-Dist: paho-mqtt
